certipy/__init__.py
certipy/entry.py
certipy/version.py
certipy/commands/__init__.py
certipy/commands/account.py
certipy/commands/auth.py
certipy/commands/ca.py
certipy/commands/cert.py
certipy/commands/find.py
certipy/commands/forge.py
certipy/commands/parse.py
certipy/commands/relay.py
certipy/commands/req.py
certipy/commands/shadow.py
certipy/commands/template.py
certipy/commands/parsers/__init__.py
certipy/commands/parsers/account.py
certipy/commands/parsers/auth.py
certipy/commands/parsers/ca.py
certipy/commands/parsers/cert.py
certipy/commands/parsers/find.py
certipy/commands/parsers/forge.py
certipy/commands/parsers/parse.py
certipy/commands/parsers/relay.py
certipy/commands/parsers/req.py
certipy/commands/parsers/shadow.py
certipy/commands/parsers/target.py
certipy/commands/parsers/template.py
certipy/lib/__init__.py
certipy/lib/certificate.py
certipy/lib/channel_binding.py
certipy/lib/constants.py
certipy/lib/errors.py
certipy/lib/files.py
certipy/lib/formatting.py
certipy/lib/http.py
certipy/lib/kerberos.py
certipy/lib/ldap.py
certipy/lib/logger.py
certipy/lib/ntlm.py
certipy/lib/pkinit.py
certipy/lib/registry.py
certipy/lib/req.py
certipy/lib/rpc.py
certipy/lib/security.py
certipy/lib/structs.py
certipy/lib/target.py
certipy/lib/time.py
certipy_ad-5.0.3.dist-info/licenses/LICENSE
certipy_ad-5.0.3.dist-info/METADATA
certipy_ad-5.0.3.dist-info/WHEEL
certipy_ad-5.0.3.dist-info/entry_points.txt
certipy_ad-5.0.3.dist-info/top_level.txt
certipy_ad-5.0.3.dist-info/RECORD
