Metadata-Version: 2.4
Name: certipy-ad
Version: 5.0.3
Summary: Active Directory Certificate Services enumeration and abuse
Author: ly4k
License: MIT
Project-URL: Homepage, https://github.com/ly4k/Certipy
Project-URL: Bug Tracker, https://github.com/ly4k/Certipy/issues
Classifier: Programming Language :: Python :: 3
Classifier: License :: OSI Approved :: MIT License
Classifier: Operating System :: OS Independent
Requires-Python: >=3.12
License-File: LICENSE
Requires-Dist: asn1crypto~=1.5.1
Requires-Dist: cryptography~=42.0.8
Requires-Dist: impacket~=0.12.0
Requires-Dist: ldap3~=2.9.1
Requires-Dist: pyasn1~=0.6.1
Requires-Dist: dnspython~=2.7.0
Requires-Dist: pyopenssl~=24.0.0
Requires-Dist: requests~=2.32.3
Requires-Dist: pycryptodome~=3.22.0
Requires-Dist: beautifulsoup4~=4.13.4
Requires-Dist: httpx~=0.28.1
Requires-Dist: argcomplete~=3.6.2
Dynamic: license-file
